{
    "Product" : [
       {
           "image_url": "https://m.media-amazon.com/images/I/71jHO2zTrnL._AC_SR255,340_.jpg",
           "name" : "Future Icon 3-Bar Tee",
           "discount" : "25%689",
           "price" : 21,
           "price1" : 330,
           "category" : "T-shirt",
           "color" : "Pink"
   
       },
       {
           "image_url": "https://m.media-amazon.com/images/I/71Juw8eDAsL._AC_SR255,340_.jpg",
           "name" : "Heathered 3G Tank",
           "discount" : "35%",
           "price" : 555,
           "price1": 770,
           "category" : "Tank Top",
           "color" : "Blue"
   
       },{
           "image_url": "https://m.media-amazon.com/images/I/71ETawgdEIL._AC_SR255,340_.jpg",
           "name" : "Badge of Sport Tee",
           "discount" : "12%",
           "price" : 225,
           "price1" : 310,
           "category" : "T-shirt",
           "color" : "Black"
   
       },{
           "image_url": "https://m.media-amazon.com/images/I/71QK+PGV22L._AC_SR255,340_.jpg",
           "name": "Tiger Camo Tee",
           "discount" : "20%",
           "price" : 435,
           "price1" : 660,
           "category" : "Tank Top",
           "color" : "White"
   
       },{
           "image_url": "https://m.media-amazon.com/images/I/81eyb5jVroS._AC_SR255,340_.jpg",
           "name" : "Beefy-T Long Sleeve Henley",
           "discount" : "30%",
           "price" : 440,
           "price1" : 770,
   
           "category" : "Activewear shirts",
           "color" : "Black"
   
       },{
           "image_url": "https://m.media-amazon.com/images/I/71sbI515BZS._AC_SR255,340_.jpg",
           "name" : "Beefy-T Long Sleeve Henley",
           "discount" : "20%",
           "price" : 540,
           "price1" : 770,
           "category" : "Activewear shirts",
           "color" : "Red"
   
       },{
           "image_url": "https://m.media-amazon.com/images/I/71dprCNVIiL._AC_SR255,340_.jpg",
           "name" : "Sport Men's Performance Quarter-Zip Pullover",
           "discount" : "30%",
           "price" : 225,
           "price1" : 345,
           "category" : "Activewear shirts",
           "color" : "Grey"
   
       },{
           "image_url": "https://m.media-amazon.com/images/I/71igqfdI6mL._AC_SR255,340_.jpg",
           "name" : "Crayon Wave Short Sleeve Tee",
           "discount" : "40%",
           "price" :318 ,
           "price1": 550 ,
   
           "category" : "Tank Top",
           "color" : "Blue"
           
       },{
           "image_url": "https://m.media-amazon.com/images/I/71FIah-lZ9L._AC_SR255,340_.jpg",
           "name" : "Billy's Burgers Short Sleeve Tee",
           "discount" : "25%",
           "price" : 327,
           "price1" : 440,
           "category" : "T-shirt",
           "color" : "White"
   
       },
       {
           "image_url": "https://m.media-amazon.com/images/I/81eQdSgMFiL._AC_SR255,340_.jpg",
           
           "name" : "Bahama Coast Paradiso",
           "discount" : "20%",
           "price" :555 ,
           "price1" : 669,
           "category" : "Activewear shirts",
           "color" : "Blue"
   
       },{
           "image_url": "https://m.media-amazon.com/images/I/81rM+ppd0VL._AC_SR255,340_.jpg",
           
           "name" : "On the Road Long Sleeve Tee",
           "discount" : "30%",
           "price" :470 ,
           "price1" : 567,
           "category" : "Activewear shirts",
           "color" : "Grey"
   
       },{
           "image_url": "https://m.media-amazon.com/images/I/818P0LgvweL._AC_SR255,340_.jpg",
           
           "name" : "On the Road Long Sleeve Tee",
           "discount" : "20%",
           "price" :428 ,
           "price1" : 536,
           "category" : "Tank Top",
           "color" : "Blue"
   
       },{
           "image_url": "https://m.media-amazon.com/images/I/71YKqYLNA7L._AC_SR255,340_.jpg",
           
           "name" : "Gold Lines",
           "discount" : "30%",
           "price" : 435,
           "price1" : 578,
           "category" : "T-shirts",
           "color" : "Black"
   
       },{
           "image_url": "https://m.media-amazon.com/images/I/71JpjPGZrpL._AC_SR255,340_.jpg",
           
           "name" : "Comp Logo Short Sleeve Tee",
           "discount": "23%",
           "price" : 123 ,
           "price1" : 189,
           "category" : "T-shirts",
           "color" : "White"
   
       },{
           "image_url": "https://m.media-amazon.com/images/I/71Tm7QTY6lL._AC_SR255,340_.jpg",
           
           "name" : "The Stretch-Cotton Shirt",
           "discount" : "32%",
           "price" :284,
           "price1" : 345,
           "category" : "Activewear shirts",
           "color" : "Grey"
   
       },{
           "image_url": "https://m.media-amazon.com/images/I/818yPP9f1aL._AC_SR255,340_.jpg",
           
           "name" : "Ainsley",
           "discount" : "20%",
           "price" : 240,
           "price1" : 440,
           "category" : "T-shirts",
           "color" : "Blue"
   
       },{
           "image_url": "https://m.media-amazon.com/images/I/71H+Rny-ZnL._AC_SR255,340_.jpg",
           "name" : "Retro Frog",
           "discount" : "30%",
           "price" : 445,
           "price1" : 555,
   
           "category" : "Activewear shirts",
           "color" : "Grey"
   
       },{
           "image_url": "https://m.media-amazon.com/images/I/71bPeBIrKAL._AC_SR255,340_.jpg",
           "name" : "Sunrise V12",
           "discount" : "20%",
           "price" : 425,
           "price1" : 660,
           "category" : "Activewear shirts",
           "color" : "Black"
   
       },
       {
           "image_url": "https://m.media-amazon.com/images/I/71feLIUWzyL._AC_SR255,340_.jpg",
           "name" : "Gradient B21",
           "discount" : "35%",
           "price" : 323,
           "price1" : 240,
           "category" : "T-shirts",
           "color" : "Red"
   
       }
   ]
}